pytest_messenger/__init__.py
pytest_messenger/dingtalk.py
pytest_messenger/plugin.py
pytest_messenger/slack.py
pytest_messenger-3.3.0.dist-info/AUTHORS.rst
pytest_messenger-3.3.0.dist-info/LICENSE
pytest_messenger-3.3.0.dist-info/METADATA
pytest_messenger-3.3.0.dist-info/WHEEL
pytest_messenger-3.3.0.dist-info/entry_points.txt
pytest_messenger-3.3.0.dist-info/top_level.txt
pytest_messenger-3.3.0.dist-info/RECORD
