Metadata-Version: 2.1
Name: pytest-messenger
Version: 3.3.0
Summary: Pytest to Slack reporting plugin
Home-page: https://github.com/pytest-dev/pytest-messenger
Author: LaserPhaser
Author-email: arseny.antonov@gmail.com
License: MIT license
Keywords: pytest,py.test,slack
Classifier: Framework :: Pytest
Classifier: Development Status :: 5 - Production/Stable
Classifier: Intended Audience :: Developers
Classifier: License :: OSI Approved :: MIT License
Classifier: Natural Language :: English
Classifier: Programming Language :: Python :: 3.6
Classifier: Programming Language :: Python :: 3.7
Classifier: Programming Language :: Python :: 3.8
Requires-Python: >=3.6
License-File: LICENSE
License-File: AUTHORS.rst
Requires-Dist: requests
